odoo8_addon_crm_rma_lot_mass_return-8.0.1.0.0.99.dev44-py3.8-nspkg.pth
odoo_addons/crm_rma_lot_mass_return/README.rst
odoo_addons/crm_rma_lot_mass_return/__init__.py
odoo_addons/crm_rma_lot_mass_return/__openerp__.py
odoo_addons/crm_rma_lot_mass_return/demo/purchase_order.xml
odoo_addons/crm_rma_lot_mass_return/demo/sale_order.xml
odoo_addons/crm_rma_lot_mass_return/demo/stock_production_lot.xml
odoo_addons/crm_rma_lot_mass_return/demo/transfer_details.xml
odoo_addons/crm_rma_lot_mass_return/i18n/am.po
odoo_addons/crm_rma_lot_mass_return/i18n/ar.po
odoo_addons/crm_rma_lot_mass_return/i18n/bg.po
odoo_addons/crm_rma_lot_mass_return/i18n/bs.po
odoo_addons/crm_rma_lot_mass_return/i18n/ca.po
odoo_addons/crm_rma_lot_mass_return/i18n/ca_ES.po
odoo_addons/crm_rma_lot_mass_return/i18n/crm_rma_lot_mass_return.pot
odoo_addons/crm_rma_lot_mass_return/i18n/cs.po
odoo_addons/crm_rma_lot_mass_return/i18n/da.po
odoo_addons/crm_rma_lot_mass_return/i18n/de.po
odoo_addons/crm_rma_lot_mass_return/i18n/el_GR.po
odoo_addons/crm_rma_lot_mass_return/i18n/en_GB.po
odoo_addons/crm_rma_lot_mass_return/i18n/es.po
odoo_addons/crm_rma_lot_mass_return/i18n/es_AR.po
odoo_addons/crm_rma_lot_mass_return/i18n/es_CL.po
odoo_addons/crm_rma_lot_mass_return/i18n/es_CO.po
odoo_addons/crm_rma_lot_mass_return/i18n/es_CR.po
odoo_addons/crm_rma_lot_mass_return/i18n/es_DO.po
odoo_addons/crm_rma_lot_mass_return/i18n/es_EC.po
odoo_addons/crm_rma_lot_mass_return/i18n/es_ES.po
odoo_addons/crm_rma_lot_mass_return/i18n/es_MX.po
odoo_addons/crm_rma_lot_mass_return/i18n/es_PA.po
odoo_addons/crm_rma_lot_mass_return/i18n/es_PE.po
odoo_addons/crm_rma_lot_mass_return/i18n/es_PY.po
odoo_addons/crm_rma_lot_mass_return/i18n/es_VE.po
odoo_addons/crm_rma_lot_mass_return/i18n/et.po
odoo_addons/crm_rma_lot_mass_return/i18n/eu.po
odoo_addons/crm_rma_lot_mass_return/i18n/fa.po
odoo_addons/crm_rma_lot_mass_return/i18n/fi.po
odoo_addons/crm_rma_lot_mass_return/i18n/fr.po
odoo_addons/crm_rma_lot_mass_return/i18n/fr_CA.po
odoo8_addon_crm_rma_lot_mass_return-8.0.1.0.0.99.dev44.dist-info/METADATA
odoo8_addon_crm_rma_lot_mass_return-8.0.1.0.0.99.dev44.dist-info/WHEEL
odoo8_addon_crm_rma_lot_mass_return-8.0.1.0.0.99.dev44.dist-info/namespace_packages.txt
odoo8_addon_crm_rma_lot_mass_return-8.0.1.0.0.99.dev44.dist-info/top_level.txt
odoo8_addon_crm_rma_lot_mass_return-8.0.1.0.0.99.dev44.dist-info/RECORD
